[
    {
        "name": "gungun gupta",
        "email": "g@123",
        "phone": "9301728257",
        "pin": 1015,
        "Account No.": "97uiCdC61",
        "balance": 2000
    },
    {
        "name": "gungun gupta",
        "email": "gungungupta875@gmail.com",
        "phone": "9301728257",
        "pin": "1015",
        "Account No.": "sc76O7X1m",
        "balance": 0
    },
    {
        "name": "gungun gupta",
        "email": "gungungupta875@gmail.com",
        "phone": "9301728257",
        "pin": "1015",
        "Account No.": "5A84SUk7W",
        "balance": 0
    },
    {
        "name": "gungun gupta",
        "email": "gungungupta875@gmail.com",
        "phone": "9301728257",
        "pin": "1015",
        "Account No.": "JL5Ws6s11",
        "balance": 0
    },
    {
        "name": "harsh gautam",
        "email": "hg1485@gmail.com",
        "phone": "8305451528",
        "pin": "2004",
        "Account No.": "j5k2h73BT",
        "balance": 5000
    }
]